doctopi/README.md
doctopi/__init__.py
doctopi/__main__.py
doctopi/cli/README.md
doctopi/cli/__init__.py
doctopi/cli/default.ini
doctopi/formatter/README.md
doctopi/formatter/__init__.py
doctopi/formatter/markdown/README.md
doctopi/formatter/markdown/__init__.py
doctopi/formatter/markdown/markdown_builder.py
doctopi/formatter/markdown/cmd/README.md
doctopi/formatter/markdown/cmd/__init__.py
doctopi/formatter/markdown/cmd/class_attr_commands.py
doctopi/formatter/markdown/cmd/class_command.py
doctopi/formatter/markdown/cmd/docstring_commands.py
doctopi/formatter/markdown/cmd/function_command.py
doctopi/formatter/markdown/cmd/param_table_command.py
doctopi/formatter/rest/README.md
doctopi/formatter/rest/__init__.py
doctopi/parser/README.md
doctopi/parser/__init__.py
doctopi/parser/parser_factory.py
doctopi/parser/cpp/README.md
doctopi/parser/cpp/__init__.py
doctopi/parser/java/README.md
doctopi/parser/java/__init__.py
doctopi/parser/python/README.md
doctopi/parser/python/__init__.py
doctopi/parser/python/docspec_adapter.py
doctopi/types/README.md
doctopi/types/__init__.py
DoctoPi-0.1.0.dist-info/LICENSE
DoctoPi-0.1.0.dist-info/METADATA
DoctoPi-0.1.0.dist-info/WHEEL
DoctoPi-0.1.0.dist-info/top_level.txt
DoctoPi-0.1.0.dist-info/RECORD
