Metadata-Version: 2.1
Name: DoctoPi
Version: 0.1.0
Summary: Extensible Python library for docs-as-code
Author-email: Jack Swiney <jack.swiney11@gmail.com>
Maintainer-email: Jack Swiney <jack.swiney11@gmail.com>
License: Apache Software License 2.0
Project-URL: bugs, https://github.com/jack-swiney/doctopi/issues
Project-URL: changelog, https://github.com/jack-swiney/doctopi/blob/master/changelog.md
Project-URL: homepage, https://github.com/jack-swiney/doctopi
License-File: LICENSE
Requires-Dist: docspec
Requires-Dist: docspec-python
Requires-Dist: docstring-parser
Requires-Dist: mdutils
Provides-Extra: dev
Requires-Dist: coverage ; extra == 'dev'
Requires-Dist: pylint ; extra == 'dev'
Requires-Dist: pytest ; extra == 'dev'
